README.md
setup.py
chatgpt/__init__.py
chatgpt/dataset/__init__.py
chatgpt/dataset/reward_dataset.py
chatgpt/dataset/utils.py
chatgpt/experience_maker/__init__.py
chatgpt/experience_maker/base.py
chatgpt/experience_maker/naive.py
chatgpt/nn/__init__.py
chatgpt/nn/actor.py
chatgpt/nn/bloom_actor.py
chatgpt/nn/bloom_critic.py
chatgpt/nn/bloom_rm.py
chatgpt/nn/critic.py
chatgpt/nn/generation.py
chatgpt/nn/generation_utils.py
chatgpt/nn/gpt_actor.py
chatgpt/nn/gpt_critic.py
chatgpt/nn/gpt_rm.py
chatgpt/nn/lora.py
chatgpt/nn/loss.py
chatgpt/nn/opt_actor.py
chatgpt/nn/opt_critic.py
chatgpt/nn/opt_rm.py
chatgpt/nn/reward_model.py
chatgpt/nn/utils.py
chatgpt/replay_buffer/__init__.py
chatgpt/replay_buffer/base.py
chatgpt/replay_buffer/naive.py
chatgpt/replay_buffer/utils.py
chatgpt/trainer/__init__.py
chatgpt/trainer/base.py
chatgpt/trainer/ppo.py
chatgpt/trainer/rm.py
chatgpt/trainer/utils.py
chatgpt/trainer/callbacks/__init__.py
chatgpt/trainer/callbacks/base.py
chatgpt/trainer/callbacks/performance_evaluator.py
chatgpt/trainer/strategies/__init__.py
chatgpt/trainer/strategies/base.py
chatgpt/trainer/strategies/colossalai.py
chatgpt/trainer/strategies/ddp.py
chatgpt/trainer/strategies/naive.py
chatgpt_python.egg-info/PKG-INFO
chatgpt_python.egg-info/SOURCES.txt
chatgpt_python.egg-info/dependency_links.txt
chatgpt_python.egg-info/requires.txt
chatgpt_python.egg-info/top_level.txt